Workbook

Sheet Token Release Schedule
A1: KNX Token Release Schedule · $32M round: $28M main close @ $0.16 + $4M top-up @ $0.20 · TGE target Q1 2027 (model working date 5 Feb 2027) · listing reference $0.20
A2: Round in two closes: Main $28.0M @ $0.16 (175M) by 31 Dec 2026, plus Top-Up $4.0M @ $0.20 (20M): 195M to new money (19.5%). Existing holders 100M, 12m cliff + 48m vest. KOLpad allocations 15M at the $0.20 reference (KOLs and Mindo commission; 20% TGE, 40% M1, 40% M2). Day-one float 5.3% (53M), itemized: venue 1 25M · venue 2 6M · Aerodrome pool 4M · MM loan 10M (returnable) · airdrop 5M · KOLpad 3M. Treasury and Foundation 0% at TGE. Emissions up to 485M (48.5%) under the declining cap. Listing reference $0.20, set at listing.
A3: Open items (yellow): second venue for the 0.6% · contents of the 2.5% venue allocation · Treasury and Foundation start months · MM sizing · top-up size · KOLpad token count moves with the listing price.
A4: Pocket | C4: Pre-seed (Brandon Torres Declet) | D4: Seed (LD Capital) | E4: Seed (Cogitent) | F4: Seed (Leland) | G4: Seed (M77) | H4: Seed (Block Maven) | I4: Seed (Covey) | J4: KOL round (T-Rex, K1, Nebula) | K4: New round: main close | L4: New round: top-up close | M4: KOLpad: KOLs and Mindo commission | N4: Mining and validator emissions | O4: Marketing and exchanges | P4: Treasury and reserves | Q4: Foundation | R4: Team and advisors | S4: Liquidity / MM | T4: Community airdrop | X4: SCENARIO SUMMARY | AA4: Emissions cap (per month)
A5: Investor / note | C5: existing | D5: existing | E5: existing | F5: existing | G5: existing | H5: existing | I5: existing | J5: existing | K5: New round: anchor and syndicate, by 31 Dec 2026 | L5: New round | M5: KOLpad Marketing Raise Agreement, as amended 17 Oct 2026 | N5: auto-balance | O5: company allocation | P5: company allocation | Q5: company allocation | R5: company allocation | S5: company allocation | T5: company allocation | X5: Existing holders (tokens / %) | Y5: =SUM(C8:J8) -> 100000000 | Z5: =Y5/1000000000 -> 0.1 | AA5: Yr 1 | AB5: 4000000
A6: $ committed | C6: 1000000 | D6: 4687500 | E6: 2812500 | F6: 1875000 | G6: 1875000 | H6: 1875000 | I6: 1875000 | J6: 500000 | K6: =K7*K8 -> 28000000 | L6: =L7*L8 -> 4000000 | M6: 0 | X6: Existing effective price | Y6: =SUM(C6:J6)/SUM(C8:J8) -> 0.165 | AA6: Yr 2 | AB6: 3400000
A7: Price / token | C7: =C6/C8 -> 0.09679235 | D7: =D6/D8 -> 0.17164511 | E7: =E6/E8 -> 0.1716451 | F7: =F6/F8 -> 0.17164509 | G7: =G6/G8 -> 0.17164509 | H7: =H6/H8 -> 0.17164509 | I7: =I6/I8 -> 0.17164509 | J7: =J6/J8 -> 0.21939601 | K7: 0.16 | L7: 0.2 | M7: =Y22 -> 0.12 | X7: New round (tokens / %) | Y7: =SUM(K8:L8) -> 195000000 | Z7: =Y7/1000000000 -> 0.195 | AA7: Yr 3 | AB7: 2890000
A8: Tokens allocated | C8: 10331395 | D8: 27309255 | E8: 16385554 | F8: 10923703 | G8: 10923703 | H8: 10923703 | I8: 10923703 | J8: 2278984 | K8: 175000000 | L8: 20000000 | M8: =Y25 -> 15000000 | N8: =1000000000-SUM(C8:M8)-SUM(O8:T8) -> 485000000 | O8: 50000000 | P8: 50000000 | Q8: 40000000 | R8: 50000000 | S8: 10000000 | T8: 5000000 | X8: New round raised | Y8: =SUM(K6:L6) -> 32000000 | AA8: Yr 4 | AB8: 2456500
A9: % of supply | C9: =C8/1000000000 -> 0.010331395 | D9: =D8/1000000000 -> 0.027309255 | E9: =E8/1000000000 -> 0.016385554 | F9: =F8/1000000000 -> 0.010923703 | G9: =G8/1000000000 -> 0.010923703 | H9: =H8/1000000000 -> 0.010923703 | I9: =I8/1000000000 -> 0.010923703 | J9: =J8/1000000000 -> 0.002278984 | ... T9: =T8/1000000000 -> 0.005 | X9: Blended new price | Y9: =Y8/Y7 -> 0.16410256 | AA9: Yr 5 | AB9: 2088025
A10: TGE unlock (tokens) | C10: 0 | D10: 0 | E10: 0 | F10: 0 | G10: 0 | H10: 0 | I10: 0 | J10: 0 | K10: 0 | L10: 0 | M10: =M8*0.2 -> 3000000 | N10: 0 | O10: 35000000 | P10: 0 | Q10: 0 | R10: 0 | S10: =S8 -> 10000000 | T10: =T8 -> 5000000 | X10: FDV @ blended price | Y10: =Y9*1000000000 -> 1.6410256e+08 | AA10: Yr 6 | AB10: 1774821.2
A11: Vesting | C11: 0% TGE; 12-mo cliff; linear M13 to M60 (48-mo) | D11: 0% TGE; 12-mo cliff; linear M13 to M60 (48-mo) | E11: 0% TGE; 12-mo cliff; linear M13 to M60 (48-mo) | F11: 0% TGE; 12-mo cliff; linear M13 to M60 (48-mo) | G11: 0% TGE; 12-mo cliff; linear M13 to M60 (48-mo) | H11: 0% TGE; 12-mo cliff; linear M13 to M60 (48-mo) | I11: 0% TGE; 12-mo cliff; linear M13 to M60 (48-mo) | J11: 0% TGE; 12-mo cliff; linear M13 to M60 (48-mo) | K11: 0% TGE; 12-mo cliff; linear M13 to M36: main close @ $0.16 | L11: 0% TGE; 12-mo cliff; linear M13 to M36: top-up close @ $0.20 | M11: 20% TGE; 40% M1; 40% M2 | N11: Cap: 48M/yr −15%/yr from M4; issuance = min(cap, usage) | O11: 35M itemized at TGE (venue 1 25 · venue 2 6 · Aerodrome 4); 15M ops linear M1 to M30 | P11: 0% TGE; linear M7 to M36 (start month TBC) | Q11: 0% TGE; linear M13 to M36 (start month TBC) | R11: 2,000,000/month M14 to M38 | S11: 10M at TGE: returnable MM loan; terms published; sizing TBC | T11: 100% at TGE: retroactive, unconditional (0.5%) | X11: Total investors % of supply | Y11: =(Y5+Y7)/1000000000 -> 0.295 | AA11: Yr 7 | AB11: 1508598.1
X12: Supply check (= 1,000,000,000) | Y12: =SUM(C8:T8) -> 1000000000 | AA12: Yr 8 | AB12: 1282308.4
X13: TGE circulating (tokens / %) | Y13: =U15 -> 53000000 | Z13: =U15/1000000000 -> 0.053
A14: Month | B14: m | C14: =C4 -> Pre-seed (Brandon Torres Declet) | D14: =D4 -> Seed (LD Capital) | E14: =E4 -> Seed (Cogitent) | F14: =F4 -> Seed (Leland) | G14: =G4 -> Seed (M77) | H14: =H4 -> Seed (Block Maven) | I14: =I4 -> Seed (Covey) | J14: =J4 -> KOL round (T-Rex, K1, Nebula) | ... T14: =T4 -> Community airdrop | U14: Circulating # | V14: Circulating % | AA14: DAY-ONE FLOAT
A15: T+0M (TGE) | B15: 0 | C15: =IF(AND($B15>=13,$B15<=60),C$8/48,0) -> 0 | D15: =IF(AND($B15>=13,$B15<=60),D$8/48,0) -> 0 | E15: =IF(AND($B15>=13,$B15<=60),E$8/48,0) -> 0 | F15: =IF(AND($B15>=13,$B15<=60),F$8/48,0) -> 0 | G15: =IF(AND($B15>=13,$B15<=60),G$8/48,0) -> 0 | H15: =IF(AND($B15>=13,$B15<=60),H$8/48,0) -> 0 | I15: =IF(AND($B15>=13,$B15<=60),I$8/48,0) -> 0 | J15: =IF(AND($B15>=13,$B15<=60),J$8/48,0) -> 0 | K15: =IF(AND($B15>=13,$B15<=36),K$8/24,0) -> 0 | L15: =IF(AND($B15>=13,$B15<=36),L$8/24,0) -> 0 | M15: =IF($B15=0,M$8*0.2,IF(OR($B15=1,$B15=2),M$8*0.4,0)) -> 3000000 | N15: =IF($B15<4,0,INDEX($AB$5:$AB$12,INT(($B15-1)/12)+1)) -> 0 | O15: =IF($B15=0,35000000,IF(AND($B15>=1,$B15<=30),15000000/30,0)) -> 35000000 | P15: =IF(AND($B15>=7,$B15<=36),P$8/30,0) -> 0 | Q15: =IF(AND($B15>=13,$B15<=36),Q$8/24,0) -> 0 | R15: =IF(AND($B15>=14,$B15<=38),R$8/25,0) -> 0 | S15: =IF($B15=0,S$8,0) -> 10000000 | T15: =IF($B15=0,T$8,0) -> 5000000 | U15: =SUM(C15:T15) -> 53000000 | V15: =U15/1000000000 -> 0.053 | X15: KOLpad tokens (tokens / %) | Y15: =M8 -> 15000000 | Z15: =M8/1000000000 -> 0.015 | AA15: Venue 1 obligations | AB15: 25000000
A16: T+1M | B16: 1 | C16: =IF(AND($B16>=13,$B16<=60),C$8/48,0) -> 0 | D16: =IF(AND($B16>=13,$B16<=60),D$8/48,0) -> 0 | E16: =IF(AND($B16>=13,$B16<=60),E$8/48,0) -> 0 | F16: =IF(AND($B16>=13,$B16<=60),F$8/48,0) -> 0 | G16: =IF(AND($B16>=13,$B16<=60),G$8/48,0) -> 0 | H16: =IF(AND($B16>=13,$B16<=60),H$8/48,0) -> 0 | I16: =IF(AND($B16>=13,$B16<=60),I$8/48,0) -> 0 | J16: =IF(AND($B16>=13,$B16<=60),J$8/48,0) -> 0 | K16: =IF(AND($B16>=13,$B16<=36),K$8/24,0) -> 0 | L16: =IF(AND($B16>=13,$B16<=36),L$8/24,0) -> 0 | M16: =IF($B16=0,M$8*0.2,IF(OR($B16=1,$B16=2),M$8*0.4,0)) -> 6000000 | N16: =IF($B16<4,0,INDEX($AB$5:$AB$12,INT(($B16-1)/12)+1)) -> 0 | O16: =IF($B16=0,35000000,IF(AND($B16>=1,$B16<=30),15000000/30,0)) -> 500000 | P16: =IF(AND($B16>=7,$B16<=36),P$8/30,0) -> 0 | Q16: =IF(AND($B16>=13,$B16<=36),Q$8/24,0) -> 0 | R16: =IF(AND($B16>=14,$B16<=38),R$8/25,0) -> 0 | S16: =IF($B16=0,S$8,0) -> 0 | T16: =IF($B16=0,T$8,0) -> 0 | U16: =U15+SUM(C16:T16) -> 59500000 | V16: =U16/1000000000 -> 0.0595 | X16: Emissions pot (tokens / %) | Y16: =N8 -> 485000000 | Z16: =N8/1000000000 -> 0.485 | AA16: Venue 2 | AB16: 6000000
A17: T+2M | B17: 2 | C17: =IF(AND($B17>=13,$B17<=60),C$8/48,0) -> 0 | D17: =IF(AND($B17>=13,$B17<=60),D$8/48,0) -> 0 | E17: =IF(AND($B17>=13,$B17<=60),E$8/48,0) -> 0 | F17: =IF(AND($B17>=13,$B17<=60),F$8/48,0) -> 0 | G17: =IF(AND($B17>=13,$B17<=60),G$8/48,0) -> 0 | H17: =IF(AND($B17>=13,$B17<=60),H$8/48,0) -> 0 | I17: =IF(AND($B17>=13,$B17<=60),I$8/48,0) -> 0 | J17: =IF(AND($B17>=13,$B17<=60),J$8/48,0) -> 0 | K17: =IF(AND($B17>=13,$B17<=36),K$8/24,0) -> 0 | L17: =IF(AND($B17>=13,$B17<=36),L$8/24,0) -> 0 | M17: =IF($B17=0,M$8*0.2,IF(OR($B17=1,$B17=2),M$8*0.4,0)) -> 6000000 | N17: =IF($B17<4,0,INDEX($AB$5:$AB$12,INT(($B17-1)/12)+1)) -> 0 | O17: =IF($B17=0,35000000,IF(AND($B17>=1,$B17<=30),15000000/30,0)) -> 500000 | P17: =IF(AND($B17>=7,$B17<=36),P$8/30,0) -> 0 | Q17: =IF(AND($B17>=13,$B17<=36),Q$8/24,0) -> 0 | R17: =IF(AND($B17>=14,$B17<=38),R$8/25,0) -> 0 | S17: =IF($B17=0,S$8,0) -> 0 | T17: =IF($B17=0,T$8,0) -> 0 | U17: =U16+SUM(C17:T17) -> 66000000 | V17: =U17/1000000000 -> 0.066 | X17: KOLPAD ALLOCATIONS | AA17: Aerodrome pool | AB17: 4000000
A18: T+3M | B18: 3 | C18: =IF(AND($B18>=13,$B18<=60),C$8/48,0) -> 0 | D18: =IF(AND($B18>=13,$B18<=60),D$8/48,0) -> 0 | E18: =IF(AND($B18>=13,$B18<=60),E$8/48,0) -> 0 | F18: =IF(AND($B18>=13,$B18<=60),F$8/48,0) -> 0 | G18: =IF(AND($B18>=13,$B18<=60),G$8/48,0) -> 0 | H18: =IF(AND($B18>=13,$B18<=60),H$8/48,0) -> 0 | I18: =IF(AND($B18>=13,$B18<=60),I$8/48,0) -> 0 | J18: =IF(AND($B18>=13,$B18<=60),J$8/48,0) -> 0 | K18: =IF(AND($B18>=13,$B18<=36),K$8/24,0) -> 0 | L18: =IF(AND($B18>=13,$B18<=36),L$8/24,0) -> 0 | M18: =IF($B18=0,M$8*0.2,IF(OR($B18=1,$B18=2),M$8*0.4,0)) -> 0 | N18: =IF($B18<4,0,INDEX($AB$5:$AB$12,INT(($B18-1)/12)+1)) -> 0 | O18: =IF($B18=0,35000000,IF(AND($B18>=1,$B18<=30),15000000/30,0)) -> 500000 | P18: =IF(AND($B18>=7,$B18<=36),P$8/30,0) -> 0 | Q18: =IF(AND($B18>=13,$B18<=36),Q$8/24,0) -> 0 | R18: =IF(AND($B18>=14,$B18<=38),R$8/25,0) -> 0 | S18: =IF($B18=0,S$8,0) -> 0 | T18: =IF($B18=0,T$8,0) -> 0 | U18: =U17+SUM(C18:T18) -> 66500000 | V18: =U18/1000000000 -> 0.0665 | X18: KOLpad contribution base ($) | Y18: 1500000 | AA18: MM loan (returnable) | AB18: 10000000
A19: T+4M | B19: 4 | C19: =IF(AND($B19>=13,$B19<=60),C$8/48,0) -> 0 | D19: =IF(AND($B19>=13,$B19<=60),D$8/48,0) -> 0 | E19: =IF(AND($B19>=13,$B19<=60),E$8/48,0) -> 0 | F19: =IF(AND($B19>=13,$B19<=60),F$8/48,0) -> 0 | G19: =IF(AND($B19>=13,$B19<=60),G$8/48,0) -> 0 | H19: =IF(AND($B19>=13,$B19<=60),H$8/48,0) -> 0 | I19: =IF(AND($B19>=13,$B19<=60),I$8/48,0) -> 0 | J19: =IF(AND($B19>=13,$B19<=60),J$8/48,0) -> 0 | K19: =IF(AND($B19>=13,$B19<=36),K$8/24,0) -> 0 | L19: =IF(AND($B19>=13,$B19<=36),L$8/24,0) -> 0 | M19: =IF($B19=0,M$8*0.2,IF(OR($B19=1,$B19=2),M$8*0.4,0)) -> 0 | N19: =IF($B19<4,0,INDEX($AB$5:$AB$12,INT(($B19-1)/12)+1)) -> 4000000 | O19: =IF($B19=0,35000000,IF(AND($B19>=1,$B19<=30),15000000/30,0)) -> 500000 | P19: =IF(AND($B19>=7,$B19<=36),P$8/30,0) -> 0 | Q19: =IF(AND($B19>=13,$B19<=36),Q$8/24,0) -> 0 | R19: =IF(AND($B19>=14,$B19<=38),R$8/25,0) -> 0 | S19: =IF($B19=0,S$8,0) -> 0 | T19: =IF($B19=0,T$8,0) -> 0 | U19: =U18+SUM(C19:T19) -> 71000000 | V19: =U19/1000000000 -> 0.071 | X19: Mindo commission (% of contributions, paid in tokens) | Y19: 0.2 | AA19: Community airdrop | AB19: 5000000
A20: T+5M | B20: 5 | C20: =IF(AND($B20>=13,$B20<=60),C$8/48,0) -> 0 | D20: =IF(AND($B20>=13,$B20<=60),D$8/48,0) -> 0 | E20: =IF(AND($B20>=13,$B20<=60),E$8/48,0) -> 0 | F20: =IF(AND($B20>=13,$B20<=60),F$8/48,0) -> 0 | G20: =IF(AND($B20>=13,$B20<=60),G$8/48,0) -> 0 | H20: =IF(AND($B20>=13,$B20<=60),H$8/48,0) -> 0 | I20: =IF(AND($B20>=13,$B20<=60),I$8/48,0) -> 0 | J20: =IF(AND($B20>=13,$B20<=60),J$8/48,0) -> 0 | K20: =IF(AND($B20>=13,$B20<=36),K$8/24,0) -> 0 | L20: =IF(AND($B20>=13,$B20<=36),L$8/24,0) -> 0 | M20: =IF($B20=0,M$8*0.2,IF(OR($B20=1,$B20=2),M$8*0.4,0)) -> 0 | N20: =IF($B20<4,0,INDEX($AB$5:$AB$12,INT(($B20-1)/12)+1)) -> 4000000 | O20: =IF($B20=0,35000000,IF(AND($B20>=1,$B20<=30),15000000/30,0)) -> 500000 | P20: =IF(AND($B20>=7,$B20<=36),P$8/30,0) -> 0 | Q20: =IF(AND($B20>=13,$B20<=36),Q$8/24,0) -> 0 | R20: =IF(AND($B20>=14,$B20<=38),R$8/25,0) -> 0 | S20: =IF($B20=0,S$8,0) -> 0 | T20: =IF($B20=0,T$8,0) -> 0 | U20: =U19+SUM(C20:T20) -> 75500000 | V20: =U20/1000000000 -> 0.0755 | X20: KOL and Mindo discount to TGE valuation | Y20: 0.4 | AA20: KOLpad (20% at TGE) | AB20: =M10 -> 3000000
A21: T+6M | B21: 6 | C21: =IF(AND($B21>=13,$B21<=60),C$8/48,0) -> 0 | D21: =IF(AND($B21>=13,$B21<=60),D$8/48,0) -> 0 | E21: =IF(AND($B21>=13,$B21<=60),E$8/48,0) -> 0 | F21: =IF(AND($B21>=13,$B21<=60),F$8/48,0) -> 0 | G21: =IF(AND($B21>=13,$B21<=60),G$8/48,0) -> 0 | H21: =IF(AND($B21>=13,$B21<=60),H$8/48,0) -> 0 | I21: =IF(AND($B21>=13,$B21<=60),I$8/48,0) -> 0 | J21: =IF(AND($B21>=13,$B21<=60),J$8/48,0) -> 0 | K21: =IF(AND($B21>=13,$B21<=36),K$8/24,0) -> 0 | L21: =IF(AND($B21>=13,$B21<=36),L$8/24,0) -> 0 | M21: =IF($B21=0,M$8*0.2,IF(OR($B21=1,$B21=2),M$8*0.4,0)) -> 0 | N21: =IF($B21<4,0,INDEX($AB$5:$AB$12,INT(($B21-1)/12)+1)) -> 4000000 | O21: =IF($B21=0,35000000,IF(AND($B21>=1,$B21<=30),15000000/30,0)) -> 500000 | P21: =IF(AND($B21>=7,$B21<=36),P$8/30,0) -> 0 | Q21: =IF(AND($B21>=13,$B21<=36),Q$8/24,0) -> 0 | R21: =IF(AND($B21>=14,$B21<=38),R$8/25,0) -> 0 | S21: =IF($B21=0,S$8,0) -> 0 | T21: =IF($B21=0,T$8,0) -> 0 | U21: =U20+SUM(C21:T21) -> 80000000 | V21: =U21/1000000000 -> 0.08 | X21: Listing reference price ($) | Y21: 0.2 | AA21: TOTAL (5.3%) | AB21: =SUM(AB15:AB20) -> 53000000
A22: T+7M | B22: 7 | C22: =IF(AND($B22>=13,$B22<=60),C$8/48,0) -> 0 | D22: =IF(AND($B22>=13,$B22<=60),D$8/48,0) -> 0 | E22: =IF(AND($B22>=13,$B22<=60),E$8/48,0) -> 0 | F22: =IF(AND($B22>=13,$B22<=60),F$8/48,0) -> 0 | G22: =IF(AND($B22>=13,$B22<=60),G$8/48,0) -> 0 | H22: =IF(AND($B22>=13,$B22<=60),H$8/48,0) -> 0 | I22: =IF(AND($B22>=13,$B22<=60),I$8/48,0) -> 0 | J22: =IF(AND($B22>=13,$B22<=60),J$8/48,0) -> 0 | K22: =IF(AND($B22>=13,$B22<=36),K$8/24,0) -> 0 | L22: =IF(AND($B22>=13,$B22<=36),L$8/24,0) -> 0 | M22: =IF($B22=0,M$8*0.2,IF(OR($B22=1,$B22=2),M$8*0.4,0)) -> 0 | N22: =IF($B22<4,0,INDEX($AB$5:$AB$12,INT(($B22-1)/12)+1)) -> 4000000 | O22: =IF($B22=0,35000000,IF(AND($B22>=1,$B22<=30),15000000/30,0)) -> 500000 | P22: =IF(AND($B22>=7,$B22<=36),P$8/30,0) -> 1666666.7 | Q22: =IF(AND($B22>=13,$B22<=36),Q$8/24,0) -> 0 | R22: =IF(AND($B22>=14,$B22<=38),R$8/25,0) -> 0 | S22: =IF($B22=0,S$8,0) -> 0 | T22: =IF($B22=0,T$8,0) -> 0 | U22: =U21+SUM(C22:T22) -> 86166667 | V22: =U22/1000000000 -> 0.086166667 | X22: Effective KOLpad token price ($) | Y22: =Y21*(1-Y20) -> 0.12
A23: T+8M | B23: 8 | C23: =IF(AND($B23>=13,$B23<=60),C$8/48,0) -> 0 | D23: =IF(AND($B23>=13,$B23<=60),D$8/48,0) -> 0 | E23: =IF(AND($B23>=13,$B23<=60),E$8/48,0) -> 0 | F23: =IF(AND($B23>=13,$B23<=60),F$8/48,0) -> 0 | G23: =IF(AND($B23>=13,$B23<=60),G$8/48,0) -> 0 | H23: =IF(AND($B23>=13,$B23<=60),H$8/48,0) -> 0 | I23: =IF(AND($B23>=13,$B23<=60),I$8/48,0) -> 0 | J23: =IF(AND($B23>=13,$B23<=60),J$8/48,0) -> 0 | K23: =IF(AND($B23>=13,$B23<=36),K$8/24,0) -> 0 | L23: =IF(AND($B23>=13,$B23<=36),L$8/24,0) -> 0 | M23: =IF($B23=0,M$8*0.2,IF(OR($B23=1,$B23=2),M$8*0.4,0)) -> 0 | N23: =IF($B23<4,0,INDEX($AB$5:$AB$12,INT(($B23-1)/12)+1)) -> 4000000 | O23: =IF($B23=0,35000000,IF(AND($B23>=1,$B23<=30),15000000/30,0)) -> 500000 | P23: =IF(AND($B23>=7,$B23<=36),P$8/30,0) -> 1666666.7 | Q23: =IF(AND($B23>=13,$B23<=36),Q$8/24,0) -> 0 | R23: =IF(AND($B23>=14,$B23<=38),R$8/25,0) -> 0 | S23: =IF($B23=0,S$8,0) -> 0 | T23: =IF($B23=0,T$8,0) -> 0 | U23: =U22+SUM(C23:T23) -> 92333333 | V23: =U23/1000000000 -> 0.092333333 | X23: KOL tokens (100% of contributions) | Y23: =ROUND(Y18/Y22,0) -> 12500000
A24: T+9M | B24: 9 | C24: =IF(AND($B24>=13,$B24<=60),C$8/48,0) -> 0 | D24: =IF(AND($B24>=13,$B24<=60),D$8/48,0) -> 0 | E24: =IF(AND($B24>=13,$B24<=60),E$8/48,0) -> 0 | F24: =IF(AND($B24>=13,$B24<=60),F$8/48,0) -> 0 | G24: =IF(AND($B24>=13,$B24<=60),G$8/48,0) -> 0 | H24: =IF(AND($B24>=13,$B24<=60),H$8/48,0) -> 0 | I24: =IF(AND($B24>=13,$B24<=60),I$8/48,0) -> 0 | J24: =IF(AND($B24>=13,$B24<=60),J$8/48,0) -> 0 | K24: =IF(AND($B24>=13,$B24<=36),K$8/24,0) -> 0 | L24: =IF(AND($B24>=13,$B24<=36),L$8/24,0) -> 0 | M24: =IF($B24=0,M$8*0.2,IF(OR($B24=1,$B24=2),M$8*0.4,0)) -> 0 | N24: =IF($B24<4,0,INDEX($AB$5:$AB$12,INT(($B24-1)/12)+1)) -> 4000000 | O24: =IF($B24=0,35000000,IF(AND($B24>=1,$B24<=30),15000000/30,0)) -> 500000 | P24: =IF(AND($B24>=7,$B24<=36),P$8/30,0) -> 1666666.7 | Q24: =IF(AND($B24>=13,$B24<=36),Q$8/24,0) -> 0 | R24: =IF(AND($B24>=14,$B24<=38),R$8/25,0) -> 0 | S24: =IF($B24=0,S$8,0) -> 0 | T24: =IF($B24=0,T$8,0) -> 0 | U24: =U23+SUM(C24:T24) -> 98500000 | V24: =U24/1000000000 -> 0.0985 | X24: Mindo commission tokens | Y24: =ROUND(Y18*Y19/Y22,0) -> 2500000
A25: T+10M | B25: 10 | C25: =IF(AND($B25>=13,$B25<=60),C$8/48,0) -> 0 | D25: =IF(AND($B25>=13,$B25<=60),D$8/48,0) -> 0 | E25: =IF(AND($B25>=13,$B25<=60),E$8/48,0) -> 0 | F25: =IF(AND($B25>=13,$B25<=60),F$8/48,0) -> 0 | G25: =IF(AND($B25>=13,$B25<=60),G$8/48,0) -> 0 | H25: =IF(AND($B25>=13,$B25<=60),H$8/48,0) -> 0 | I25: =IF(AND($B25>=13,$B25<=60),I$8/48,0) -> 0 | J25: =IF(AND($B25>=13,$B25<=60),J$8/48,0) -> 0 | K25: =IF(AND($B25>=13,$B25<=36),K$8/24,0) -> 0 | L25: =IF(AND($B25>=13,$B25<=36),L$8/24,0) -> 0 | M25: =IF($B25=0,M$8*0.2,IF(OR($B25=1,$B25=2),M$8*0.4,0)) -> 0 | N25: =IF($B25<4,0,INDEX($AB$5:$AB$12,INT(($B25-1)/12)+1)) -> 4000000 | O25: =IF($B25=0,35000000,IF(AND($B25>=1,$B25<=30),15000000/30,0)) -> 500000 | P25: =IF(AND($B25>=7,$B25<=36),P$8/30,0) -> 1666666.7 | Q25: =IF(AND($B25>=13,$B25<=36),Q$8/24,0) -> 0 | R25: =IF(AND($B25>=14,$B25<=38),R$8/25,0) -> 0 | S25: =IF($B25=0,S$8,0) -> 0 | T25: =IF($B25=0,T$8,0) -> 0 | U25: =U24+SUM(C25:T25) -> 1.0466667e+08 | V25: =U25/1000000000 -> 0.10466667 | X25: KOLpad tokens, total | Y25: =Y23+Y24 -> 15000000
A26: T+11M | B26: 11 | C26: =IF(AND($B26>=13,$B26<=60),C$8/48,0) -> 0 | D26: =IF(AND($B26>=13,$B26<=60),D$8/48,0) -> 0 | E26: =IF(AND($B26>=13,$B26<=60),E$8/48,0) -> 0 | F26: =IF(AND($B26>=13,$B26<=60),F$8/48,0) -> 0 | G26: =IF(AND($B26>=13,$B26<=60),G$8/48,0) -> 0 | H26: =IF(AND($B26>=13,$B26<=60),H$8/48,0) -> 0 | I26: =IF(AND($B26>=13,$B26<=60),I$8/48,0) -> 0 | J26: =IF(AND($B26>=13,$B26<=60),J$8/48,0) -> 0 | K26: =IF(AND($B26>=13,$B26<=36),K$8/24,0) -> 0 | L26: =IF(AND($B26>=13,$B26<=36),L$8/24,0) -> 0 | M26: =IF($B26=0,M$8*0.2,IF(OR($B26=1,$B26=2),M$8*0.4,0)) -> 0 | N26: =IF($B26<4,0,INDEX($AB$5:$AB$12,INT(($B26-1)/12)+1)) -> 4000000 | O26: =IF($B26=0,35000000,IF(AND($B26>=1,$B26<=30),15000000/30,0)) -> 500000 | P26: =IF(AND($B26>=7,$B26<=36),P$8/30,0) -> 1666666.7 | Q26: =IF(AND($B26>=13,$B26<=36),Q$8/24,0) -> 0 | R26: =IF(AND($B26>=14,$B26<=38),R$8/25,0) -> 0 | S26: =IF($B26=0,S$8,0) -> 0 | T26: =IF($B26=0,T$8,0) -> 0 | U26: =U25+SUM(C26:T26) -> 1.1083333e+08 | V26: =U26/1000000000 -> 0.11083333 | X26: Notional value at listing reference ($) | Y26: =Y25*Y21 -> 3000000
A27: T+12M | B27: 12 | C27: =IF(AND($B27>=13,$B27<=60),C$8/48,0) -> 0 | D27: =IF(AND($B27>=13,$B27<=60),D$8/48,0) -> 0 | E27: =IF(AND($B27>=13,$B27<=60),E$8/48,0) -> 0 | F27: =IF(AND($B27>=13,$B27<=60),F$8/48,0) -> 0 | G27: =IF(AND($B27>=13,$B27<=60),G$8/48,0) -> 0 | H27: =IF(AND($B27>=13,$B27<=60),H$8/48,0) -> 0 | I27: =IF(AND($B27>=13,$B27<=60),I$8/48,0) -> 0 | J27: =IF(AND($B27>=13,$B27<=60),J$8/48,0) -> 0 | K27: =IF(AND($B27>=13,$B27<=36),K$8/24,0) -> 0 | L27: =IF(AND($B27>=13,$B27<=36),L$8/24,0) -> 0 | M27: =IF($B27=0,M$8*0.2,IF(OR($B27=1,$B27=2),M$8*0.4,0)) -> 0 | N27: =IF($B27<4,0,INDEX($AB$5:$AB$12,INT(($B27-1)/12)+1)) -> 4000000 | O27: =IF($B27=0,35000000,IF(AND($B27>=1,$B27<=30),15000000/30,0)) -> 500000 | P27: =IF(AND($B27>=7,$B27<=36),P$8/30,0) -> 1666666.7 | Q27: =IF(AND($B27>=13,$B27<=36),Q$8/24,0) -> 0 | R27: =IF(AND($B27>=14,$B27<=38),R$8/25,0) -> 0 | S27: =IF($B27=0,S$8,0) -> 0 | T27: =IF($B27=0,T$8,0) -> 0 | U27: =U26+SUM(C27:T27) -> 117000000 | V27: =U27/1000000000 -> 0.117 | X27: TGE unlock check: row 10 total vs month-0 row | Y27: =SUM(C10:T10)-U15 -> 0
A28: T+13M | B28: 13 | C28: =IF(AND($B28>=13,$B28<=60),C$8/48,0) -> 215237.4 | D28: =IF(AND($B28>=13,$B28<=60),D$8/48,0) -> 568942.81 | E28: =IF(AND($B28>=13,$B28<=60),E$8/48,0) -> 341365.71 | F28: =IF(AND($B28>=13,$B28<=60),F$8/48,0) -> 227577.15 | G28: =IF(AND($B28>=13,$B28<=60),G$8/48,0) -> 227577.15 | H28: =IF(AND($B28>=13,$B28<=60),H$8/48,0) -> 227577.15 | I28: =IF(AND($B28>=13,$B28<=60),I$8/48,0) -> 227577.15 | J28: =IF(AND($B28>=13,$B28<=60),J$8/48,0) -> 47478.833 | K28: =IF(AND($B28>=13,$B28<=36),K$8/24,0) -> 7291666.7 | L28: =IF(AND($B28>=13,$B28<=36),L$8/24,0) -> 833333.33 | M28: =IF($B28=0,M$8*0.2,IF(OR($B28=1,$B28=2),M$8*0.4,0)) -> 0 | N28: =IF($B28<4,0,INDEX($AB$5:$AB$12,INT(($B28-1)/12)+1)) -> 3400000 | O28: =IF($B28=0,35000000,IF(AND($B28>=1,$B28<=30),15000000/30,0)) -> 500000 | P28: =IF(AND($B28>=7,$B28<=36),P$8/30,0) -> 1666666.7 | Q28: =IF(AND($B28>=13,$B28<=36),Q$8/24,0) -> 1666666.7 | R28: =IF(AND($B28>=14,$B28<=38),R$8/25,0) -> 0 | S28: =IF($B28=0,S$8,0) -> 0 | T28: =IF($B28=0,T$8,0) -> 0 | U28: =U27+SUM(C28:T28) -> 1.3444167e+08 | V28: =U28/1000000000 -> 0.13444167
A29: T+14M | B29: 14 | C29: =IF(AND($B29>=13,$B29<=60),C$8/48,0) -> 215237.4 | D29: =IF(AND($B29>=13,$B29<=60),D$8/48,0) -> 568942.81 | E29: =IF(AND($B29>=13,$B29<=60),E$8/48,0) -> 341365.71 | F29: =IF(AND($B29>=13,$B29<=60),F$8/48,0) -> 227577.15 | G29: =IF(AND($B29>=13,$B29<=60),G$8/48,0) -> 227577.15 | H29: =IF(AND($B29>=13,$B29<=60),H$8/48,0) -> 227577.15 | I29: =IF(AND($B29>=13,$B29<=60),I$8/48,0) -> 227577.15 | J29: =IF(AND($B29>=13,$B29<=60),J$8/48,0) -> 47478.833 | K29: =IF(AND($B29>=13,$B29<=36),K$8/24,0) -> 7291666.7 | L29: =IF(AND($B29>=13,$B29<=36),L$8/24,0) -> 833333.33 | M29: =IF($B29=0,M$8*0.2,IF(OR($B29=1,$B29=2),M$8*0.4,0)) -> 0 | N29: =IF($B29<4,0,INDEX($AB$5:$AB$12,INT(($B29-1)/12)+1)) -> 3400000 | O29: =IF($B29=0,35000000,IF(AND($B29>=1,$B29<=30),15000000/30,0)) -> 500000 | P29: =IF(AND($B29>=7,$B29<=36),P$8/30,0) -> 1666666.7 | Q29: =IF(AND($B29>=13,$B29<=36),Q$8/24,0) -> 1666666.7 | R29: =IF(AND($B29>=14,$B29<=38),R$8/25,0) -> 2000000 | S29: =IF($B29=0,S$8,0) -> 0 | T29: =IF($B29=0,T$8,0) -> 0 | U29: =U28+SUM(C29:T29) -> 1.5388333e+08 | V29: =U29/1000000000 -> 0.15388333
A30: T+15M | B30: 15 | C30: =IF(AND($B30>=13,$B30<=60),C$8/48,0) -> 215237.4 | D30: =IF(AND($B30>=13,$B30<=60),D$8/48,0) -> 568942.81 | E30: =IF(AND($B30>=13,$B30<=60),E$8/48,0) -> 341365.71 | F30: =IF(AND($B30>=13,$B30<=60),F$8/48,0) -> 227577.15 | G30: =IF(AND($B30>=13,$B30<=60),G$8/48,0) -> 227577.15 | H30: =IF(AND($B30>=13,$B30<=60),H$8/48,0) -> 227577.15 | I30: =IF(AND($B30>=13,$B30<=60),I$8/48,0) -> 227577.15 | J30: =IF(AND($B30>=13,$B30<=60),J$8/48,0) -> 47478.833 | K30: =IF(AND($B30>=13,$B30<=36),K$8/24,0) -> 7291666.7 | L30: =IF(AND($B30>=13,$B30<=36),L$8/24,0) -> 833333.33 | M30: =IF($B30=0,M$8*0.2,IF(OR($B30=1,$B30=2),M$8*0.4,0)) -> 0 | N30: =IF($B30<4,0,INDEX($AB$5:$AB$12,INT(($B30-1)/12)+1)) -> 3400000 | O30: =IF($B30=0,35000000,IF(AND($B30>=1,$B30<=30),15000000/30,0)) -> 500000 | P30: =IF(AND($B30>=7,$B30<=36),P$8/30,0) -> 1666666.7 | Q30: =IF(AND($B30>=13,$B30<=36),Q$8/24,0) -> 1666666.7 | R30: =IF(AND($B30>=14,$B30<=38),R$8/25,0) -> 2000000 | S30: =IF($B30=0,S$8,0) -> 0 | T30: =IF($B30=0,T$8,0) -> 0 | U30: =U29+SUM(C30:T30) -> 173325000 | V30: =U30/1000000000 -> 0.173325
A31: T+16M | B31: 16 | C31: =IF(AND($B31>=13,$B31<=60),C$8/48,0) -> 215237.4 | D31: =IF(AND($B31>=13,$B31<=60),D$8/48,0) -> 568942.81 | E31: =IF(AND($B31>=13,$B31<=60),E$8/48,0) -> 341365.71 | F31: =IF(AND($B31>=13,$B31<=60),F$8/48,0) -> 227577.15 | G31: =IF(AND($B31>=13,$B31<=60),G$8/48,0) -> 227577.15 | H31: =IF(AND($B31>=13,$B31<=60),H$8/48,0) -> 227577.15 | I31: =IF(AND($B31>=13,$B31<=60),I$8/48,0) -> 227577.15 | J31: =IF(AND($B31>=13,$B31<=60),J$8/48,0) -> 47478.833 | K31: =IF(AND($B31>=13,$B31<=36),K$8/24,0) -> 7291666.7 | L31: =IF(AND($B31>=13,$B31<=36),L$8/24,0) -> 833333.33 | M31: =IF($B31=0,M$8*0.2,IF(OR($B31=1,$B31=2),M$8*0.4,0)) -> 0 | N31: =IF($B31<4,0,INDEX($AB$5:$AB$12,INT(($B31-1)/12)+1)) -> 3400000 | O31: =IF($B31=0,35000000,IF(AND($B31>=1,$B31<=30),15000000/30,0)) -> 500000 | P31: =IF(AND($B31>=7,$B31<=36),P$8/30,0) -> 1666666.7 | Q31: =IF(AND($B31>=13,$B31<=36),Q$8/24,0) -> 1666666.7 | R31: =IF(AND($B31>=14,$B31<=38),R$8/25,0) -> 2000000 | S31: =IF($B31=0,S$8,0) -> 0 | T31: =IF($B31=0,T$8,0) -> 0 | U31: =U30+SUM(C31:T31) -> 1.9276667e+08 | V31: =U31/1000000000 -> 0.19276667
A32: T+17M | B32: 17 | C32: =IF(AND($B32>=13,$B32<=60),C$8/48,0) -> 215237.4 | D32: =IF(AND($B32>=13,$B32<=60),D$8/48,0) -> 568942.81 | E32: =IF(AND($B32>=13,$B32<=60),E$8/48,0) -> 341365.71 | F32: =IF(AND($B32>=13,$B32<=60),F$8/48,0) -> 227577.15 | G32: =IF(AND($B32>=13,$B32<=60),G$8/48,0) -> 227577.15 | H32: =IF(AND($B32>=13,$B32<=60),H$8/48,0) -> 227577.15 | I32: =IF(AND($B32>=13,$B32<=60),I$8/48,0) -> 227577.15 | J32: =IF(AND($B32>=13,$B32<=60),J$8/48,0) -> 47478.833 | K32: =IF(AND($B32>=13,$B32<=36),K$8/24,0) -> 7291666.7 | L32: =IF(AND($B32>=13,$B32<=36),L$8/24,0) -> 833333.33 | M32: =IF($B32=0,M$8*0.2,IF(OR($B32=1,$B32=2),M$8*0.4,0)) -> 0 | N32: =IF($B32<4,0,INDEX($AB$5:$AB$12,INT(($B32-1)/12)+1)) -> 3400000 | O32: =IF($B32=0,35000000,IF(AND($B32>=1,$B32<=30),15000000/30,0)) -> 500000 | P32: =IF(AND($B32>=7,$B32<=36),P$8/30,0) -> 1666666.7 | Q32: =IF(AND($B32>=13,$B32<=36),Q$8/24,0) -> 1666666.7 | R32: =IF(AND($B32>=14,$B32<=38),R$8/25,0) -> 2000000 | S32: =IF($B32=0,S$8,0) -> 0 | T32: =IF($B32=0,T$8,0) -> 0 | U32: =U31+SUM(C32:T32) -> 2.1220833e+08 | V32: =U32/1000000000 -> 0.21220833
A33: T+18M | B33: 18 | C33: =IF(AND($B33>=13,$B33<=60),C$8/48,0) -> 215237.4 | D33: =IF(AND($B33>=13,$B33<=60),D$8/48,0) -> 568942.81 | E33: =IF(AND($B33>=13,$B33<=60),E$8/48,0) -> 341365.71 | F33: =IF(AND($B33>=13,$B33<=60),F$8/48,0) -> 227577.15 | G33: =IF(AND($B33>=13,$B33<=60),G$8/48,0) -> 227577.15 | H33: =IF(AND($B33>=13,$B33<=60),H$8/48,0) -> 227577.15 | I33: =IF(AND($B33>=13,$B33<=60),I$8/48,0) -> 227577.15 | J33: =IF(AND($B33>=13,$B33<=60),J$8/48,0) -> 47478.833 | K33: =IF(AND($B33>=13,$B33<=36),K$8/24,0) -> 7291666.7 | L33: =IF(AND($B33>=13,$B33<=36),L$8/24,0) -> 833333.33 | M33: =IF($B33=0,M$8*0.2,IF(OR($B33=1,$B33=2),M$8*0.4,0)) -> 0 | N33: =IF($B33<4,0,INDEX($AB$5:$AB$12,INT(($B33-1)/12)+1)) -> 3400000 | O33: =IF($B33=0,35000000,IF(AND($B33>=1,$B33<=30),15000000/30,0)) -> 500000 | P33: =IF(AND($B33>=7,$B33<=36),P$8/30,0) -> 1666666.7 | Q33: =IF(AND($B33>=13,$B33<=36),Q$8/24,0) -> 1666666.7 | R33: =IF(AND($B33>=14,$B33<=38),R$8/25,0) -> 2000000 | S33: =IF($B33=0,S$8,0) -> 0 | T33: =IF($B33=0,T$8,0) -> 0 | U33: =U32+SUM(C33:T33) -> 231650000 | V33: =U33/1000000000 -> 0.23165
A34: T+19M | B34: 19 | C34: =IF(AND($B34>=13,$B34<=60),C$8/48,0) -> 215237.4 | D34: =IF(AND($B34>=13,$B34<=60),D$8/48,0) -> 568942.81 | E34: =IF(AND($B34>=13,$B34<=60),E$8/48,0) -> 341365.71 | F34: =IF(AND($B34>=13,$B34<=60),F$8/48,0) -> 227577.15 | G34: =IF(AND($B34>=13,$B34<=60),G$8/48,0) -> 227577.15 | H34: =IF(AND($B34>=13,$B34<=60),H$8/48,0) -> 227577.15 | I34: =IF(AND($B34>=13,$B34<=60),I$8/48,0) -> 227577.15 | J34: =IF(AND($B34>=13,$B34<=60),J$8/48,0) -> 47478.833 | K34: =IF(AND($B34>=13,$B34<=36),K$8/24,0) -> 7291666.7 | L34: =IF(AND($B34>=13,$B34<=36),L$8/24,0) -> 833333.33 | M34: =IF($B34=0,M$8*0.2,IF(OR($B34=1,$B34=2),M$8*0.4,0)) -> 0 | N34: =IF($B34<4,0,INDEX($AB$5:$AB$12,INT(($B34-1)/12)+1)) -> 3400000 | O34: =IF($B34=0,35000000,IF(AND($B34>=1,$B34<=30),15000000/30,0)) -> 500000 | P34: =IF(AND($B34>=7,$B34<=36),P$8/30,0) -> 1666666.7 | Q34: =IF(AND($B34>=13,$B34<=36),Q$8/24,0) -> 1666666.7 | R34: =IF(AND($B34>=14,$B34<=38),R$8/25,0) -> 2000000 | S34: =IF($B34=0,S$8,0) -> 0 | T34: =IF($B34=0,T$8,0) -> 0 | U34: =U33+SUM(C34:T34) -> 2.5109167e+08 | V34: =U34/1000000000 -> 0.25109167
A35: T+20M | B35: 20 | C35: =IF(AND($B35>=13,$B35<=60),C$8/48,0) -> 215237.4 | D35: =IF(AND($B35>=13,$B35<=60),D$8/48,0) -> 568942.81 | E35: =IF(AND($B35>=13,$B35<=60),E$8/48,0) -> 341365.71 | F35: =IF(AND($B35>=13,$B35<=60),F$8/48,0) -> 227577.15 | G35: =IF(AND($B35>=13,$B35<=60),G$8/48,0) -> 227577.15 | H35: =IF(AND($B35>=13,$B35<=60),H$8/48,0) -> 227577.15 | I35: =IF(AND($B35>=13,$B35<=60),I$8/48,0) -> 227577.15 | J35: =IF(AND($B35>=13,$B35<=60),J$8/48,0) -> 47478.833 | K35: =IF(AND($B35>=13,$B35<=36),K$8/24,0) -> 7291666.7 | L35: =IF(AND($B35>=13,$B35<=36),L$8/24,0) -> 833333.33 | M35: =IF($B35=0,M$8*0.2,IF(OR($B35=1,$B35=2),M$8*0.4,0)) -> 0 | N35: =IF($B35<4,0,INDEX($AB$5:$AB$12,INT(($B35-1)/12)+1)) -> 3400000 | O35: =IF($B35=0,35000000,IF(AND($B35>=1,$B35<=30),15000000/30,0)) -> 500000 | P35: =IF(AND($B35>=7,$B35<=36),P$8/30,0) -> 1666666.7 | Q35: =IF(AND($B35>=13,$B35<=36),Q$8/24,0) -> 1666666.7 | R35: =IF(AND($B35>=14,$B35<=38),R$8/25,0) -> 2000000 | S35: =IF($B35=0,S$8,0) -> 0 | T35: =IF($B35=0,T$8,0) -> 0 | U35: =U34+SUM(C35:T35) -> 2.7053333e+08 | V35: =U35/1000000000 -> 0.27053333
A36: T+21M | B36: 21 | C36: =IF(AND($B36>=13,$B36<=60),C$8/48,0) -> 215237.4 | D36: =IF(AND($B36>=13,$B36<=60),D$8/48,0) -> 568942.81 | E36: =IF(AND($B36>=13,$B36<=60),E$8/48,0) -> 341365.71 | F36: =IF(AND($B36>=13,$B36<=60),F$8/48,0) -> 227577.15 | G36: =IF(AND($B36>=13,$B36<=60),G$8/48,0) -> 227577.15 | H36: =IF(AND($B36>=13,$B36<=60),H$8/48,0) -> 227577.15 | I36: =IF(AND($B36>=13,$B36<=60),I$8/48,0) -> 227577.15 | J36: =IF(AND($B36>=13,$B36<=60),J$8/48,0) -> 47478.833 | K36: =IF(AND($B36>=13,$B36<=36),K$8/24,0) -> 7291666.7 | L36: =IF(AND($B36>=13,$B36<=36),L$8/24,0) -> 833333.33 | M36: =IF($B36=0,M$8*0.2,IF(OR($B36=1,$B36=2),M$8*0.4,0)) -> 0 | N36: =IF($B36<4,0,INDEX($AB$5:$AB$12,INT(($B36-1)/12)+1)) -> 3400000 | O36: =IF($B36=0,35000000,IF(AND($B36>=1,$B36<=30),15000000/30,0)) -> 500000 | P36: =IF(AND($B36>=7,$B36<=36),P$8/30,0) -> 1666666.7 | Q36: =IF(AND($B36>=13,$B36<=36),Q$8/24,0) -> 1666666.7 | R36: =IF(AND($B36>=14,$B36<=38),R$8/25,0) -> 2000000 | S36: =IF($B36=0,S$8,0) -> 0 | T36: =IF($B36=0,T$8,0) -> 0 | U36: =U35+SUM(C36:T36) -> 289975000 | V36: =U36/1000000000 -> 0.289975
A37: T+22M | B37: 22 | C37: =IF(AND($B37>=13,$B37<=60),C$8/48,0) -> 215237.4 | D37: =IF(AND($B37>=13,$B37<=60),D$8/48,0) -> 568942.81 | E37: =IF(AND($B37>=13,$B37<=60),E$8/48,0) -> 341365.71 | F37: =IF(AND($B37>=13,$B37<=60),F$8/48,0) -> 227577.15 | G37: =IF(AND($B37>=13,$B37<=60),G$8/48,0) -> 227577.15 | H37: =IF(AND($B37>=13,$B37<=60),H$8/48,0) -> 227577.15 | I37: =IF(AND($B37>=13,$B37<=60),I$8/48,0) -> 227577.15 | J37: =IF(AND($B37>=13,$B37<=60),J$8/48,0) -> 47478.833 | K37: =IF(AND($B37>=13,$B37<=36),K$8/24,0) -> 7291666.7 | L37: =IF(AND($B37>=13,$B37<=36),L$8/24,0) -> 833333.33 | M37: =IF($B37=0,M$8*0.2,IF(OR($B37=1,$B37=2),M$8*0.4,0)) -> 0 | N37: =IF($B37<4,0,INDEX($AB$5:$AB$12,INT(($B37-1)/12)+1)) -> 3400000 | O37: =IF($B37=0,35000000,IF(AND($B37>=1,$B37<=30),15000000/30,0)) -> 500000 | P37: =IF(AND($B37>=7,$B37<=36),P$8/30,0) -> 1666666.7 | Q37: =IF(AND($B37>=13,$B37<=36),Q$8/24,0) -> 1666666.7 | R37: =IF(AND($B37>=14,$B37<=38),R$8/25,0) -> 2000000 | S37: =IF($B37=0,S$8,0) -> 0 | T37: =IF($B37=0,T$8,0) -> 0 | U37: =U36+SUM(C37:T37) -> 3.0941667e+08 | V37: =U37/1000000000 -> 0.30941667
A38: T+23M | B38: 23 | C38: =IF(AND($B38>=13,$B38<=60),C$8/48,0) -> 215237.4 | D38: =IF(AND($B38>=13,$B38<=60),D$8/48,0) -> 568942.81 | E38: =IF(AND($B38>=13,$B38<=60),E$8/48,0) -> 341365.71 | F38: =IF(AND($B38>=13,$B38<=60),F$8/48,0) -> 227577.15 | G38: =IF(AND($B38>=13,$B38<=60),G$8/48,0) -> 227577.15 | H38: =IF(AND($B38>=13,$B38<=60),H$8/48,0) -> 227577.15 | I38: =IF(AND($B38>=13,$B38<=60),I$8/48,0) -> 227577.15 | J38: =IF(AND($B38>=13,$B38<=60),J$8/48,0) -> 47478.833 | K38: =IF(AND($B38>=13,$B38<=36),K$8/24,0) -> 7291666.7 | L38: =IF(AND($B38>=13,$B38<=36),L$8/24,0) -> 833333.33 | M38: =IF($B38=0,M$8*0.2,IF(OR($B38=1,$B38=2),M$8*0.4,0)) -> 0 | N38: =IF($B38<4,0,INDEX($AB$5:$AB$12,INT(($B38-1)/12)+1)) -> 3400000 | O38: =IF($B38=0,35000000,IF(AND($B38>=1,$B38<=30),15000000/30,0)) -> 500000 | P38: =IF(AND($B38>=7,$B38<=36),P$8/30,0) -> 1666666.7 | Q38: =IF(AND($B38>=13,$B38<=36),Q$8/24,0) -> 1666666.7 | R38: =IF(AND($B38>=14,$B38<=38),R$8/25,0) -> 2000000 | S38: =IF($B38=0,S$8,0) -> 0 | T38: =IF($B38=0,T$8,0) -> 0 | U38: =U37+SUM(C38:T38) -> 3.2885833e+08 | V38: =U38/1000000000 -> 0.32885833
A39: T+24M | B39: 24 | C39: =IF(AND($B39>=13,$B39<=60),C$8/48,0) -> 215237.4 | D39: =IF(AND($B39>=13,$B39<=60),D$8/48,0) -> 568942.81 | E39: =IF(AND($B39>=13,$B39<=60),E$8/48,0) -> 341365.71 | F39: =IF(AND($B39>=13,$B39<=60),F$8/48,0) -> 227577.15 | G39: =IF(AND($B39>=13,$B39<=60),G$8/48,0) -> 227577.15 | H39: =IF(AND($B39>=13,$B39<=60),H$8/48,0) -> 227577.15 | I39: =IF(AND($B39>=13,$B39<=60),I$8/48,0) -> 227577.15 | J39: =IF(AND($B39>=13,$B39<=60),J$8/48,0) -> 47478.833 | K39: =IF(AND($B39>=13,$B39<=36),K$8/24,0) -> 7291666.7 | L39: =IF(AND($B39>=13,$B39<=36),L$8/24,0) -> 833333.33 | M39: =IF($B39=0,M$8*0.2,IF(OR($B39=1,$B39=2),M$8*0.4,0)) -> 0 | N39: =IF($B39<4,0,INDEX($AB$5:$AB$12,INT(($B39-1)/12)+1)) -> 3400000 | O39: =IF($B39=0,35000000,IF(AND($B39>=1,$B39<=30),15000000/30,0)) -> 500000 | P39: =IF(AND($B39>=7,$B39<=36),P$8/30,0) -> 1666666.7 | Q39: =IF(AND($B39>=13,$B39<=36),Q$8/24,0) -> 1666666.7 | R39: =IF(AND($B39>=14,$B39<=38),R$8/25,0) -> 2000000 | S39: =IF($B39=0,S$8,0) -> 0 | T39: =IF($B39=0,T$8,0) -> 0 | U39: =U38+SUM(C39:T39) -> 348300000 | V39: =U39/1000000000 -> 0.3483
... A75: T+60M | B75: 60 | C75: =IF(AND($B75>=13,$B75<=60),C$8/48,0) -> 215237.4 | D75: =IF(AND($B75>=13,$B75<=60),D$8/48,0) -> 568942.81 | E75: =IF(AND($B75>=13,$B75<=60),E$8/48,0) -> 341365.71 | F75: =IF(AND($B75>=13,$B75<=60),F$8/48,0) -> 227577.15 | G75: =IF(AND($B75>=13,$B75<=60),G$8/48,0) -> 227577.15 | H75: =IF(AND($B75>=13,$B75<=60),H$8/48,0) -> 227577.15 | I75: =IF(AND($B75>=13,$B75<=60),I$8/48,0) -> 227577.15 | J75: =IF(AND($B75>=13,$B75<=60),J$8/48,0) -> 47478.833 | K75: =IF(AND($B75>=13,$B75<=36),K$8/24,0) -> 0 | L75: =IF(AND($B75>=13,$B75<=36),L$8/24,0) -> 0 | M75: =IF($B75=0,M$8*0.2,IF(OR($B75=1,$B75=2),M$8*0.4,0)) -> 0 | N75: =IF($B75<4,0,INDEX($AB$5:$AB$12,INT(($B75-1)/12)+1)) -> 2088025 | O75: =IF($B75=0,35000000,IF(AND($B75>=1,$B75<=30),15000000/30,0)) -> 0 | P75: =IF(AND($B75>=7,$B75<=36),P$8/30,0) -> 0 | Q75: =IF(AND($B75>=13,$B75<=36),Q$8/24,0) -> 0 | R75: =IF(AND($B75>=14,$B75<=38),R$8/25,0) -> 0 | S75: =IF($B75=0,S$8,0) -> 0 | T75: =IF($B75=0,T$8,0) -> 0 | U75: =U74+SUM(C75:T75) -> 6.810143e+08 | V75: =U75/1000000000 -> 0.6810143

Sheet InvestorInsiders Breakdown
A1: Investor, team and advisor breakdown. Investor-room copy: individual wallet addresses are held in tier 2.
A6: Investor/Insiders breakdown (full cap table) -- add rows if necessary | L6: Top 10 investors (excluding team) | N6: Divide by the current circulating supply in Token Release Schedule tab
A7: Date | B7: Investment Round | C7: Cost per token | D7: Investor | E7: No. of Tokens Issued | F7: Allocation % | G7: ETH/BNB/USDT Contribution Address | H7: FDV | I7: Amount Raised | J7: Token Receiving Address | L7: Wallet Identity | M7: Wallet Address | N7: % of circulating supply | O7: % of total supply | P7: Token Receiving Address
B8: Equity | C8: n/a | D8: Investor 0 - Brandon Torres Declet - Equity | E8: n/a | F8: n/a | G8: n/a | H8: n/a | I8: 2000000 | J8: n/a
B9: Pre-Seed | C9: 0.09679235 | D9: Investor 1 - Brandon Torres Declet - Pre Seed Investor | E9: 10331395 | F9: 0.010331395 | G9: N/A | H9: =C9*1000000000 -> 96792350 | I9: =C9*E9 -> 1000000 | J9: Held in tier 2
A10: 18/12/2025 | B10: Seed | C10: 0.17164511 | D10: Investor 2 - LD Capital - Seed Investor | E10: 27309255 | F10: 0.027309255 | G10: N/A | H10: =C10*1000000000 -> 1.7164511e+08 | I10: =C10*E10 -> 4687500 | J10: Held in tier 2
A11: 13/12/2025 | B11: Seed | C11: 0.1716451 | D11: Investor 3 - Cogitent - Seed Investor | E11: 16385554 | F11: 0.016385554 | G11: N/A | H11: =C11*1000000000 -> 1.716451e+08 | I11: =C11*E11 -> 2812500 | J11: Held in tier 2
A12: 19/12/2025 | B12: Seed | C12: 0.17164509 | D12: Investor 4 - Leland - Seed Investor | E12: 10923703 | F12: 0.010923703 | G12: N/A | H12: =C12*1000000000 -> 1.7164509e+08 | I12: =C12*E12 -> 1875000 | J12: Held in tier 2
A13: 13/12/2025 | B13: Seed | C13: 0.17164509 | D13: Investor 5 - M77 - Seed Investor | E13: 10923703 | F13: 0.010923703 | G13: N/A | H13: =C13*1000000000 -> 1.7164509e+08 | I13: =C13*E13 -> 1875000 | J13: Held in tier 2
A14: 46174 | B14: Seed | C14: 0.17164509 | D14: Investor 6 - Block Maven - Seed Investor | E14: 10923703 | F14: 0.010923703 | G14: N/A | H14: =C14*1000000000 -> 1.7164509e+08 | I14: =C14*E14 -> 1875000 | J14: Held in tier 2
A15: 13/12/2025 | B15: Seed | C15: 0.17164509 | D15: Investor 7 - Covey - Seed Investor | E15: 10923703 | F15: 0.010923703 | G15: N/A | H15: =C15*1000000000 -> 1.7164509e+08 | I15: =C15*E15 -> 1875000 | J15: Held in tier 2
B16: Seed | C16: 0.21939601 | D16: Investor 8 - KOL Round | E16: 2278984 | F16: 0.002278984 | G16: N/A | H16: =C16*1000000000 -> 2.1939601e+08 | I16: =C16*E16 -> 500000 | J16: Held in tier 2
B17: New round: main close (2026) | C17: 0.16 | D17: New money, main close: anchor + syndicate (names & wallets at close) | E17: 175000000 | F17: 0.175 | G17: N/A | H17: =C17*1000000000 -> 160000000 | I17: =C17*E17 -> 28000000 | J17: TBC
B18: New round: top-up close | C18: 0.2 | D18: New money, top-up close at $0.20 ($200M FDV) | E18: 20000000 | F18: 0.02 | H18: =C18*1000000000 -> 200000000 | I18: =C18*E18 -> 4000000 | J18: TBC
E20: =SUM(E9:E19) -> 295000000 | F20: =SUM(F9:F19) -> 0.295 | I20: =SUM(I9:I19) -> 48500000 | J20: Make sure the number equals to the checker
D21: Checker | E21: =SUM('Token Release Schedule'!C8:L8) -> 295000000 | F21: =SUM('Token Release Schedule'!C9:L9) -> 0.295 | H21: Checker | I21: =SUM('Token Release Schedule'!C6:L6) -> 48500000 | J21: The check links to the master tab
A22: Team breakdown (key members only)
A23: Date | B23: Team Member Name | C23: Job Role / Scope | D23: No. of Tokens Issued | E23: Allocation % | F23: ETH/BNB/USDT Contribution Address | G23: Token Receiving Address
B24: Jon Ollwerther | C24: Chairman | D24: 10000000 | E24: 0.01
B25: Pablo Pérez Pazos | C25: Chief Business Development Officer | D25: 10000000 | E25: 0.01
B26: Team reserve (future hires) | C26: TBD | D26: 17500000 | E26: 0.0175
D35: =SUM(D24:D34) -> 37500000 | E35: =SUM(E24:E34) -> 0.0375 | F35: Make sure the number equals to the checker
C36: Checker | D36: ='Token Release Schedule'!R8-D50 -> 37500000 | E36: ='Token Release Schedule'!R9-E50 -> 0.0375 | F36: The check links to the master tab
A37: Advisor breakdown | L37: Identity of Top 10 existing token holders (if token is already circulating)
A38: Date | B38: Advisor | C38: Job Role / Scope | D38: No. of Tokens Issued | E38: Allocation % | F38: ETH/BNB/USDT Contribution Address | G38: Token Receiving Address | L38: Wallet Identity | M38: Wallet Address | N38: Description | O38: % of total supply
B39: Brandon Torres Declet | C39: President | D39: 10000000 | E39: 0.01 | L39: Not applicable: the token is not yet circulating
B40: Lucas Van Oostrum | C40: Advisor | D40: 2500000 | E40: 0.0025
D50: =SUM(D39:D49) -> 12500000 | E50: =SUM(E39:E49) -> 0.0125 | F50: Make sure the number equals to the checker
C51: Checker | D51: ='Token Release Schedule'!R8-D35 -> 12500000 | E51: ='Token Release Schedule'!R9-E35 -> 0.0125 | F51: The check links to the master tab

Sheet Monetary Policy
B2: Monetary Policy, Emission Type and Supply Descriptions
B4: 1. Monetary Policy
B5: THI | C5: A) Fixed Supply
B6: B) Non Capped Supply | C6: B) Non Capped Supply (Inflationary based on emmission type)
B7: C) Non-Programmatic Deflationary | C7: C) Non-Programmatic Deflationary: Supply shrinks over time due to non-programmatic mechanisms such as burns (e.g., BNB)
B8: D) Programmatic Deflationary | C8: D) Programmatic Deflationary: Supply shrinks over time due to programmatic mechanism (burn schedule, slashing penalties, % of tx value burnt, etc.)
B9: E) Burn and Mint Equilibrium | C9: E) Burn and Mint Equilibrium: Tokens burned and, separately, protocol mints new tokens per period. (e.g., Factom)
B10: F) Other | C10: F) Other
B12: 2. Emission Type
B13: A) Increasing Issuance | C13: A) Increasing Issuance: Amount of coins generated per period (block, day, year), increases over time.
B14: B) Fixed Inflation Rate | C14: B) Fixed Inflation Rate: Increasing issuance based on a fixed inflation rate per period of time (block, day, year).
B15: D) Decreasing Inflation Rate | C15: D) Decreasing Inflation Rate: Depending on reduction rate of inflation, this model can lead to an increasing, fixed or decreasing issuance per period.
B16: E) Decreasing Issuance | C16: E) Decreasing Issuance: The amount of coins generated per period (block, day, year) decreases over time. Leads to an exponential decrease of the inflation rate. (e.g., Bitcoin)
B17: F) Dynamic Issuance and Inflation Rate | C17: F) Dynamic Issuance and Inflation Rate: Amount of coins generated per period (block, day, year) or the inflation rate, depend on specific network conditions such as the % of network staking. (E.g., Cosmos monetary policy targeting a total network stake)
B18: E) Other | C18: E) Other
B20: KNX: Monetary Policy = A) Fixed Supply - 1,000,000,000 max, with 100% of protocol revenue to open-market buy-and-burn from TGE (programmatic deflationary pressure). Emission Type = E) Decreasing Issuance - hard annual cap of 48M KNX in year 1 stepping down 15%/yr; actual issuance = the lesser of the cap and a usage-linked formula (KNX per verified attested task, halving annually).
